download_aptnotes/__init__.py
download_aptnotes/__main__.py
download_aptnotes/cli.py
download_aptnotes/downloading.py
download_aptnotes/main.py
download_aptnotes/parsing.py
download_aptnotes/saving.py
download_aptnotes/utils.py
download_aptnotes-0.1.0.dist-info/entry_points.txt
download_aptnotes-0.1.0.dist-info/LICENSE
download_aptnotes-0.1.0.dist-info/WHEEL
download_aptnotes-0.1.0.dist-info/METADATA
download_aptnotes-0.1.0.dist-info/RECORD
