Metadata-Version: 2.1
Name: download-aptnotes
Version: 0.1.0
Summary: Download and (optionally) parse APTNotes quickly and easily
Home-page: https://github.com/nikstur/download-aptnotes
License: GPL-3.0-or-later
Keywords: aptnotes,apt,infosec,data
Author: nikstur
Requires-Python: >=3.8,<4.0
Classifier: License :: OSI Approved :: GNU General Public License v3 or later (GPLv3+)
Classifier: Programming Language :: Python :: 3
Classifier: Programming Language :: Python :: 3.8
Classifier: Programming Language :: Python :: 3.9
Provides-Extra: tika
Requires-Dist: aiofiles (>=0.6.0,<0.7.0)
Requires-Dist: aiohttp[speedups] (>=3.7.3,<4.0.0)
Requires-Dist: aiosqlite (>=0.16.0,<0.17.0)
Requires-Dist: beautifulsoup4[lxml] (>=4.9.3,<5.0.0)
Requires-Dist: janus (>=0.6.1,<0.7.0)
Requires-Dist: tika (>=1.24,<2.0); extra == "tika"
Requires-Dist: typer[all] (>=0.3.2,<0.4.0)
Requires-Dist: uvloop (>=0.14.0,<0.15.0)
Project-URL: Repository, https://github.com/nikstur/download-aptnotes
